{"Place.e387ef53-ea7c-4efe-a595-dda6082f608e": {"city_id": "2000", "user_id": "", "name": "", "description": "", "number_rooms": 0, "number_bathrooms": 0, "max_guest": 0, "price_by_night": 0, "latitude": 2.0, "longitude": 0.0, "amenity_ids": "", "id": "e387ef53-ea7c-4efe-a595-dda6082f608e", "created_at": "2024-02-06T19:27:42.548184", "updated_at": "2024-02-06T19:27:42.548195", "__class__": "Place"}, "BaseModel.31179eed-a057-46d4-a8ff-f8a00be98ca0": {"id": "31179eed-a057-46d4-a8ff-f8a00be98ca0", "created_at": "2024-02-08T19:57:12.374332", "updated_at": "2024-02-08T19:57:12.374338", "__class__": "BaseModel"}}